pymultimatic/__init__.py
pymultimatic/systemmanager.py
pymultimatic/api/__init__.py
pymultimatic/api/connector.py
pymultimatic/api/defaults.py
pymultimatic/api/error.py
pymultimatic/api/payloads.py
pymultimatic/api/payloads_senso.py
pymultimatic/api/schemas.py
pymultimatic/api/urls.py
pymultimatic/api/urls_senso.py
pymultimatic/model/__init__.py
pymultimatic/model/common.py
pymultimatic/model/constants.py
pymultimatic/model/dhw.py
pymultimatic/model/info.py
pymultimatic/model/mapper.py
pymultimatic/model/mode.py
pymultimatic/model/quick_mode.py
pymultimatic/model/report.py
pymultimatic/model/room.py
pymultimatic/model/status.py
pymultimatic/model/syncstate.py
pymultimatic/model/system.py
pymultimatic/model/timeprogram.py
pymultimatic/model/ventilation.py
pymultimatic/model/zone.py
pymultimatic/utils/__init__.py
pymultiMATIC-0.7.3.dist-info/LICENSE
pymultiMATIC-0.7.3.dist-info/METADATA
pymultiMATIC-0.7.3.dist-info/WHEEL
pymultiMATIC-0.7.3.dist-info/top_level.txt
pymultiMATIC-0.7.3.dist-info/RECORD
