Metadata-Version: 2.1
Name: pymultiMATIC
Version: 0.7.3
Summary: Python interface with Vaillant multiMATIC
Home-page: https://github.com/thomasgermain/pymultiMATIC.git
Author: Thomas Germain
Author-email: 12560542+thomasgermain@users.noreply.github.com
License: MIT
Classifier: License :: OSI Approved :: MIT License
Classifier: Development Status :: 4 - Beta
Classifier: Programming Language :: Python
Classifier: Programming Language :: Python :: 3.8
Classifier: Programming Language :: Python :: 3.9
Classifier: Programming Language :: Python :: 3.10
Classifier: Programming Language :: Python :: 3.11
Classifier: Topic :: Home Automation
License-File: LICENSE
Requires-Dist: attrs <24.0.0,>=23.0.0
Requires-Dist: aiohttp <4.0.0,>=3.8.0
Requires-Dist: schema <0.8.0,>=0.7.4
